Workbook

Sheet 2026 Bid Tracker
A1: Job ID | B1: Month | C1: Client | D1: Project Name | E1: Bid Due Date | F1: Drawing Stage | G1: Bid Type | H1: Sent Date | I1: Sub. Method | J1: Status | K1: Win? | L1: Job Type | M1: Est. Bid Value | N1: Link: Drawings | O1: Link: Specs | P1: Link: Schedule | Q1: Notes | R1: Bid Feedback | S1: NTP Received? | T1: Final Cost | U1: Profit Margin ($) | V1: CO Link | W1: Lessons Learned
B2: January
A3: Q-26-003 | C3: Viking | D3: Legacy Good Sam Pharmacy Retrofit | E3: 46038 | F3: CD | G3: Hard Bid | H3: 01/16/2026 | I3: Email | J3: Won | K3: =IF(J3="Won","✔","") -> ✔ | M3: 47988
A4: Q-26-004 | C4: Brian Kasler | D4: Ktichen & Bath Cabinets | E4: 46041 | F4: Email | G4: Budget | H4: 01/19/2026 | I4: Email | J4: Sent | K4: =IF(J4="Won","✔","") | L4: Residential | M4: 58551
A5: Q-26-005 | C5: Schommer & Sons | D5: Tualatin Park Office Reno | E5: 46044 | F5: Bid Set | G5: Hard Bid | H5: 01/22/2026 | I5: BuildingConnected | J5: Sent | K5: =IF(J5="Won","✔","") | L5: Renovation | M5: 9481
A6: Q-26-006 | C6: Ross Builder | D6: Tualatin Park Office Reno | E6: 46044 | F6: Bid Set | G6: Hard Bid | H6: 01/22/2026 | I6: BuildingConnected | J6: Sent | K6: =IF(J6="Won","✔","") | L6: Renovation | M6: 9481
A7: Q-26-007 | C7: Legacy Salmon Creek | D7: 527 Closet Cab | E7: 46038 | F7: Email | G7: Hard Bid | H7: 01/16/2026 | I7: Email | J7: Sent | K7: =IF(J7="Won","✔","") | L7: Healthcare | M7: 1052
A8: Q-26-008 | C8: Norwest | D8: Gresham Advanced Dentistry | E8: 46034 | F8: Email | G8: Budget | H8: 01/14/2026 | I8: Email | J8: Sent | K8: =IF(J8="Won","✔","") | L8: Dental | M8: 6150
A9: Q-26-009 | C9: Tim- TRBLDG Servies | D9: NW Primary Care- SE Mallard Way | E9: 46036 | F9: Email | G9: Hard Bid | H9: 01/14/2026 | I9: Email | J9: Won | K9: =IF(J9="Won","✔","") -> ✔ | M9: 1900
A10: Q-26-010 | C10: Manion Design | D10: Back Bar Cabs | E10: 46037 | F10: Email | G10: Hard Bid | I10: Email | J10: Won | K10: =IF(J10="Won","✔","") -> ✔ | M10: 2325
A11: Q-26-011 | C11: OHSU HMC | D11: 8th Ave Ste 205 | E11: 46038 | F11: Email | G11: Hard Bid | H11: 01/16/2026 | I11: Email | J11: Sent | K11: =IF(J11="Won","✔","") | L11: Healthcare | M11: 1147
A12: Q-26-012 | C12: OHSU HMC | D12: Rm 1321 Countertop | E12: 46037 | F12: Email | G12: Hard Bid | I12: Email | J12: Won | K12: =IF(J12="Won","✔","") -> ✔ | L12: Healthcare | M12: 1180
A13: Q-26-013 | C13: Idea Interiors | D13: Coats & Tails Lobby Remodel | E13: 46036 | F13: Email | G13: Hard Bid | I13: Email | J13: Won | K13: =IF(J13="Won","✔","") -> ✔ | L13: Commercial TI | M13: 3920
A14: Q-26-014 | C14: Five Star | D14: Meridian Park FSB- Corian CT | E14: 46036 | F14: Email | G14: Hard Bid | H14: 01/14/2026 | I14: Email | J14: Sent | K14: =IF(J14="Won","✔","") | M14: 7218
A15: Q-26-015 | C15: Five Star | D15: Systems Cabinets | E15: 46037 | F15: Email | I15: Email | J15: Sent | K15: =IF(J15="Won","✔","") | M15: 35919
A16: Q-26-016 | C16: Five Star | D16: Emanuel Rm 1611 | E16: 46037 | F16: Email | G16: Hard Bid | H16: 01/14/2026 | I16: Email | J16: Won | K16: =IF(J16="Won","✔","") -> ✔ | L16: Healthcare | M16: 5713
A17: Q-26-017 | B17: On Hold | C17: Wilammette Falls | D17: Behavioral Sloped Corian | J17: On Hold | K17: =IF(J17="Won","✔","")
A18: Q-26-018 | C18: Wilammette Falls | D18: ICU Corian CT | E18: 46037 | F18: Email | G18: Hard Bid | H18: 01/15/2026 | I18: Email | J18: Sent | K18: =IF(J18="Won","✔","") | L18: Hospital | M18: 3715
A19: Q-26-019 | C19: Wilammette Falls | D19: 17 Cab Drawers w/ servo drive | E19: 46037 | F19: Email | G19: Hard Bid | I19: Email | J19: Sent | K19: =IF(J19="Won","✔","") | L19: Hospital | M19: 9930
A20: Q-26-020 | C20: VAM | D20: Aligned Hillsboro Campus | E20: 46037 | F20: Email | G20: Hard Bid | I20: Email | J20: Won | K20: =IF(J20="Won","✔","") -> ✔ | L20: Commercial | M20: 3622
A21: Q-26-021 | C21: Norwest | D21: Stones Dental- Added Scope/ Sterile Revision | K21: =IF(J21="Won","✔","")
A22: Q-26-022 | C22: Trainor | D22: Herman Miller Wood Ceiling Install | E22: 46043 | F22: Email | G22: Hard Bid | H22: 01/21/2026 | I22: Email | J22: Sent | K22: =IF(J22="Won","✔","") | L22: Commercial | M22: 25800
A23: Q-26-023 | C23: Trainor | D23: Design Within Reach | E23: 46043 | F23: Email | G23: Hard Bid | H23: 01/21/2026 | I23: Email | J23: Sent | K23: =IF(J23="Won","✔","") | L23: Commercial
A24: Q-26-024 | C24: Robert Hakes | D24: Elite Recovery | E24: 46044 | F24: Email | G24: Hard Bid | K24: =IF(J24="Won","✔","") | M24: 3350
A25: Q-26-025 | C25: Essex | D25: Bonneville St Johns | E25: 46041 | F25: Email | G25: Hard Bid | H25: 46023 | I25: Email | J25: Won | K25: =IF(J25="Won","✔","") -> ✔ | M25: 3845
A26: Q-26-026 | C26: Andersen | D26: Meadowlark Place | E26: 46045 | F26: Email | G26: Hard Bid | H26: 01/23/2026 | I26: Email | J26: Sent | K26: =IF(J26="Won","✔","") | L26: Healthcare | M26: 89846
A27: Q-26-027 | C27: LMC | D27: Meadowlark Place | E27: 46049 | F27: Bid Set | G27: Hard Bid | H27: 01/23/2026 | I27: BuildingConnected | J27: Sent | K27: =IF(J27="Won","✔","") | L27: Healthcare | M27: 89846
A28: Q-26-028 | C28: Viking | D28: Legacy GS WHA Expansion | E28: 46042 | F28: Bid Set | G28: Hard Bid | H28: 01/20/2026 | I28: Email | J28: Sent | K28: =IF(J28="Won","✔","") | L28: Healthcare | M28: 86074
A29: Q-26-029 | C29: Viking | D29: Legacy EMC Trauma Relocation | E29: 46042 | F29: 50% SD | G29: Budget | H29: 01/20/2026 | I29: Email | J29: Sent | K29: =IF(J29="Won","✔","") | L29: Healthcare, Renovation | M29: 65183
A30: Q-26-030 | C30: Cameron's Chok Dee | D30: Pacific Towers Ste 1012 Revised Layout | E30: 46042 | F30: Bid Set | G30: Hard Bid | H30: 01/20/2026 | I30: Email | J30: Won | K30: =IF(J30="Won","✔","") -> ✔ | L30: Commercial | M30: 9290
A31: Q-26-031 | C31: CCDC | D31: 153 Volcano View- Cam's Casework | E31: 46049 | F31: Email | G31: Design Assist | H31: 02/06/2026 | I31: Email | J31: Sent | K31: =IF(J31="Won","✔","") | M31: 4114
A32: Q-26-032 | C32: Inline | D32: Pacific University Dining Cabs & CT | E32: 46044 | F32: Email | G32: Hard Bid | H32: 01/22/2026 | I32: Email | J32: Sent | K32: =IF(J32="Won","✔","") | M32: 5125
A33: Q-26-033 | C33: Design Build | D33: NW Urology Price 3 base Cabs | E33: 46048 | F33: Email | H33: 01/26/2026 | I33: Email | J33: Sent | K33: =IF(J33="Won","✔","") | L33: Healthcare | M33: 1430
A34: Q-26-034 | C34: Five Star | D34: Legacy Silverton Purple Casework | E34: 46048 | F34: Email | G34: Hard Bid | H34: 01/26/2026 | I34: Email | J34: Sent | K34: =IF(J34="Won","✔","") | L34: Healthcare, Renovation | M34: 4726
A35: Q-26-035 | C35: Trainor Construction | D35: Design Within Reach | E35: 46037 | F35: Email | G35: Hard Bid | H35: 01/15/2026 | I35: Email | J35: Won | K35: =IF(J35="Won","✔","") -> ✔ | L35: TI, Commercial | M35: 22923
B36: February
A37: Q-26-037 | C37: Norwest | D37: Clemons Oral Surgery | E37: 46055 | F37: Email | G37: Hard Bid | H37: 02/02/2026 | I37: Procore | J37: Client Lost | K37: =IF(J37="Won","✔","") | L37: Dental | M37: 102519 | Q37: We beat Gunderson
A38: Q-26-038 | B38: 01/22/2026 | C38: Norwest | D38: Legacy TOC OBGYN Expansion | E38: 46055 | F38: 100% DD | G38: Hard Bid | H38: 02/02/2026 | I38: Procore | J38: Sent | K38: =IF(J38="Won","✔","") | L38: Healthcare, TI | M38: 91705
A39: Q-26-039 | C39: Viking | D39: Legacy TOC OBGYN Expansion | E39: 46057 | F39: 100% DD | G39: Hard Bid | H39: 02/02/2026 | I39: Email | J39: Sent | K39: =IF(J39="Won","✔","") | L39: Healthcare, TI | M39: 99349
A40: Q-26-040 | C40: Five Star | D40: Legacy TOC OBGYN Expansion | E40: 46058 | F40: 100% DD | G40: Hard Bid | H40: 02/02/2026 | I40: Email | J40: Sent | K40: =IF(J40="Won","✔","") | L40: Healthcare, TI | M40: 99349
A41: Q-26-041 | B41: 01/27/2026 | C41: Norwest | D41: NW Windermere | E41: 46059 | F41: 100% DD | G41: Budget | H41: 01/29/2026 | I41: Procore | J41: Sent | K41: =IF(J41="Won","✔","") | L41: Healthcare | M41: 102814 | Q41: V1: Quartz and Veneer V2: Furniture ALTs V3: All P-Lam
A42: Q-26-042 | C42: Robert Hakes | D42: Pacific Office Automation | E42: 46059 | F42: Email | G42: Hard Bid | H42: 02/06/2026 | I42: Email | J42: Won | K42: =IF(J42="Won","✔","") -> ✔ | M42: 8057
A43: Q-26-043 | C43: Norwest | D43: TOC Plastic Surgery | E43: 46063 | F43: 100% SD | G43: Budget | H43: 02/09/2026 | I43: Procore | J43: Sent | K43: =IF(J43="Won","✔","") | L43: Healthcare, Renovation, TI | M43: 51640
A44: Q-26-044 | C44: CCDC | D44: Park Tower 4- Suite 209 | E44: 46062 | F44: Bid Set | G44: Hard Bid | H44: 02/09/2026 | I44: Email | J44: Sent | K44: =IF(J44="Won","✔","") | L44: Commercial, TI | M44: 8454
A45: Q-26-045 | C45: PMB | D45: Peacehealth Phys Pavilion Ste 100 | E45: 46063 | F45: Bid Set | G45: Hard Bid | H45: 02/10/2026 | I45: Email | J45: Sent | K45: =IF(J45="Won","✔","") | M45: 9099
A46: Q-26-046 | B46: 11/19/2025 | C46: Viking | D46: Adventist Health 3rd Floor// Digestive Health | E46: 46066 | F46: 100% DD | G46: Hard Bid | H46: 02/13/2026 | I46: Email | J46: Sent | K46: =IF(J46="Won","✔","") | L46: Healthcare | M46: 280677
A47: Q-26-047 | C47: Jubitz | D47: New Cabs | E47: 46066 | F47: Bid Set | G47: Hard Bid | H47: 02/07/2026 | I47: Email | J47: Won | K47: =IF(J47="Won","✔","") -> ✔ | L47: Commercial, Renovation | M47: 5960
A48: Q-26-048 | C48: Robert Hakes | D48: St Andrews Church RR | E48: 46073 | F48: Bid Set | G48: Hard Bid | I48: Email | J48: Won | K48: =IF(J48="Won","✔","") -> ✔ | M48: 13731
A49: Q-26-049 | C49: Norwest | D49: Eye health NW Admin Remodel | E49: 46075 | F49: 100% SD | G49: Budget | I49: Procore | J49: Won | K49: =IF(J49="Won","✔","") -> ✔ | L49: Healthcare | M49: 9340
A50: Q-26-050 | C50: Five Star | D50: Emanuel Rm 5403 | E50: 46064 | F50: Email | G50: Hard Bid | I50: Email | J50: Sent | K50: =IF(J50="Won","✔","") | L50: Healthcare, Renovation, Hospital | M50: 6024
A51: Q-26-051 | C51: Robert Hakes | D51: Divine Complexion | E51: 46064 | F51: Email | G51: Hard Bid | H51: 02/11/2026 | I51: Email | J51: Sent | K51: =IF(J51="Won","✔","") | L51: TI, Healthcare, Commercial | M51: 14834
A52: Q-26-052 | C52: Norwest | D52: ROSECITY HEAD & NECK SURGERY | E52: 46059 | F52: 100% SD | G52: Hard Bid | H52: 02/06/2026 | I52: Email | J52: Won | K52: =IF(J52="Won","✔","") -> ✔ | L52: Healthcare | M52: 33285
A53: Q-26-053 | C53: Mackin's Auto | D53: Office Remodel | E53: 46066 | F53: Email | G53: Hard Bid | H53: 02/13/2026 | I53: Email | J53: Won | K53: =IF(J53="Won","✔","") -> ✔ | M53: 4593
A54: Q-26-054 | C54: Five Star | D54: Emanuel Countertop | E54: 46069 | F54: Email | G54: Budget | H54: 02/24/2026 | I54: Email | J54: Sent | K54: =IF(J54="Won","✔","") | M54: 7990
A55: Q-26-055 | C55: Pacific Crest | D55: Blue Ox | E55: 46076 | F55: Email | G55: Hard Bid | H55: 02/24/2026 | I55: Email | J55: Client Lost | K55: =IF(J55="Won","✔","") | L55: Commercial, TI | M55: 60849
A56: Q-26-056 | C56: Essex | D56: D&T Excavation Shop | E56: 46070 | F56: Permit | G56: Hard Bid | H56: 02/16/2026 | I56: Email | J56: Sent | K56: =IF(J56="Won","✔","") | L56: Commercial | M56: 15945
A57: Q-26-057 | C57: Robert Hakes | D57: Rhodes Chiropractic | E57: 46066 | F57: Email | G57: Hard Bid | H57: 02/13/2026 | I57: Email | J57: Sent | K57: =IF(J57="Won","✔","") | L57: Healthcare, Renovation | M57: 12412
A58: Q-26-058 | C58: LMHMC | D58: Exam Rms | E58: 46069 | F58: Email | G58: Hard Bid | H58: 02/16/2026 | I58: Email | J58: Sent | K58: =IF(J58="Won","✔","") | L58: Healthcare, Hospital, Renovation | M58: 4968
A59: Q-26-059 | C59: LMHMC | D59: PLAM Repairs | E59: 46069 | F59: Email | G59: Hard Bid | H59: 02/16/2026 | I59: Email | J59: Sent | K59: =IF(J59="Won","✔","") | L59: Healthcare, Hospital, Renovation | M59: 1150
A60: Q-26-060 | C60: Norwest | D60: Skinwise Reception Desk | E60: 46073 | F60: Email | G60: Design Assist | I60: Email | J60: Sent | K60: =IF(J60="Won","✔","") | L60: Healthcare, Commercial | M60: 14000
A61: Q-26-061 | C61: Robert Hakes | D61: RHS- RS Medical | E61: 46073 | F61: Email | G61: Hard Bid | H61: 02/19/2026 | I61: Email | J61: Sent | K61: =IF(J61="Won","✔","") | L61: Healthcare, Renovation | M61: 9224
A62: Q-26-062 | C62: Andersen | D62: Legacy SMC Outpatient Pharmacy | E62: 46080 | F62: Email | G62: Hard Bid | H62: 02/25/2026 | I62: Email | J62: Won | K62: =IF(J62="Won","✔","") -> ✔ | L62: Healthcare, Renovation | M62: 36209
A63: Q-26-063 | C63: Robert Hakes | D63: Westside Behavioral Therapy | E63: 46080 | F63: Email | G63: Hard Bid | H63: 02/26/2026 | I63: Email | J63: Sent | K63: =IF(J63="Won","✔","") | L63: Healthcare | M63: 23410
B64: March
A65: Q-26-065 | B65: 03/01/2026 | C65: Andersen | D65: Prov St. Vincent CVL 7 | E65: 46083 | F65: CD | G65: Hard Bid | H65: 03/02/2026 | I65: Email | J65: Sent | K65: =IF(J65="Won","✔","") | L65: Hospital, Renovation | M65: 31283
A66: Q-26-066 | B66: 03/02/2026 | C66: Pence | D66: PeaceHealth Vancouver Rehab Hospital | E66: 46091 | F66: CD | G66: Hard Bid | H66: 03/11/2026 | I66: ConstructConnect | J66: Sent | K66: =IF(J66="Won","✔","") | L66: Hospital | M66: 709104
A67: Q-26-067 | B67: 03/03/2026 | C67: Howard S Wright | D67: PeaceHealth Vancouver Rehab Hospital | E67: 46091 | F67: CD | G67: Hard Bid | H67: 03/11/2026 | I67: BuildingConnected | J67: Sent | K67: =IF(J67="Won","✔","") | L67: Hospital | M67: 709104
A68: Q-26-068 | B68: 03/04/2026 | C68: Andersen | D68: PeaceHealth Vancouver Rehab Hospital | E68: 46091 | F68: CD | G68: Hard Bid | H68: 03/11/2026 | I68: BuildingConnected | J68: Sent | K68: =IF(J68="Won","✔","") | L68: Hospital | M68: 641981
A69: Q-26-069 | B69: 03/05/2026 | C69: Inline | D69: Pac U VOA East Family Relief Center | E69: 46083 | F69: Bid Set | G69: Hard Bid | J69: Sent | K69: =IF(J69="Won","✔","") | M69: 9850
A70: Q-26-070 | B70: 03/06/2026 | C70: Norwest | D70: Livewell Animal Hospital - Skyview | E70: 45727 | F70: Bid Set | G70: Hard Bid | H70: 03/11/2026 | I70: Procore | J70: Client Backed Out | K70: =IF(J70="Won","✔","") | M70: 139732
A71: Q-26-071 | B71: 03/07/2026 | C71: Norwest | D71: Livewell Animal Hospital - Tigard | E71: 46084 | F71: Bid Set | G71: Hard Bid | H71: 03/03/2026 | I71: Procore | J71: Client Backed Out | K71: =IF(J71="Won","✔","") | L71: Vet, TI | M71: 108196
A72: Q-26-072 | B72: 03/08/2026 | C72: Robert Hakes | D72: Eastside Ortho | E72: 46085 | F72: Bid Set | G72: Hard Bid | H72: 03/03/2026 | I72: Email | J72: Sent | K72: =IF(J72="Won","✔","") | L72: Healthcare, TI | M72: 87898
A73: Q-26-073 | B73: 03/09/2026 | C73: Robert Hakes | D73: Boulevard ALP | E73: 46085 | F73: Bid Set | G73: Hard Bid | H73: 03/04/2026 | I73: Email | J73: Sent | K73: =IF(J73="Won","✔","") | L73: Healthcare | M73: 6836
A74: Q-26-074 | B74: 03/10/2026 | C74: LCL | D74: LSC CT#1 Replacement | E74: 46085 | F74: Bid Set | G74: Hard Bid | H74: 03/04/2026 | I74: BuildingConnected | J74: Sent | K74: =IF(J74="Won","✔","") | L74: Healthcare | M74: 17485
A75: Q-26-075 | B75: 03/11/2026 | C75: Mortenson | D75: Kaiser WMC Gen Rad | E75: 46084 | F75: Bid Set | G75: Hard Bid | H75: 03/03/2026 | I75: BuildingConnected | J75: Sent | K75: =IF(J75="Won","✔","") | L75: Healthcare, Hospital, Renovation | M75: 5638
A76: Q-26-076 | B76: 03/12/2026 | C76: Andersen | D76: UO Acoustic Lab- Added Soffit and Cabs | E76: 46085 | F76: Permit | G76: Hard Bid | H76: 03/04/2026 | I76: Email | J76: Sent | K76: =IF(J76="Won","✔","") | L76: School | M76: 23822
A77: Q-26-077 | B77: 03/13/2026 | C77: OHSU | D77: Forest Grove PC Break RM | E77: 46085 | F77: Email | G77: Hard Bid | H77: 03/04/2026 | I77: Email | J77: Won | K77: =IF(J77="Won","✔","") -> ✔ | M77: 4681
A78: Q-26-078 | B78: 03/14/2026 | C78: Norwest | D78: Greenburg COR #2 - Private Office CT | E78: 46090 | F78: Email | G78: Hard Bid | H78: 03/09/2026 | I78: Procore | J78: Won | K78: =IF(J78="Won","✔","") -> ✔ | L78: Dental, Renovation | M78: 1392
A79: Q-26-079 | B79: 03/15/2026 | C79: First Cascade | D79: Sandy City Hall | E79: 46091 | F79: Bid Set | G79: Hard Bid | H79: 03/10/2026 | I79: BuildingConnected | J79: Sent | K79: =IF(J79="Won","✔","") | L79: Renovation | M79: 16862
A80: Q-26-080 | B80: 03/16/2026 | C80: Inline | D80: PPS Cesar Chavez Window Sills | E80: 46091 | F80: Bid Set | G80: Hard Bid | H80: 03/10/2026 | I80: BuildingConnected | J80: Sent | K80: =IF(J80="Won","✔","") | L80: School, Renovation | M80: 16254
A81: Q-26-081 | B81: 03/17/2026 | C81: Norwest | D81: Laurelhurst Dental COR #3 | E81: 46091 | F81: Email | G81: Change Order | H81: 03/10/2026 | I81: Email | J81: Won | K81: =IF(J81="Won","✔","") -> ✔ | M81: 1002
A82: Q-26-082 | B82: 03/18/2026 | C82: Norwest | D82: Windermere Office Shelving Budget | E82: 46091 | F82: Email | G82: Budget | H82: 03/10/2026 | I82: Email | J82: Sent | K82: =IF(J82="Won","✔","") | L82: Commercial, TI | M82: 18904
A83: Q-26-083 | B83: 03/19/2026 | C83: Robert Hakes | D83: Therapeutic Associates Hazel Dell | E83: 46094 | F83: Email | G83: Hard Bid | H83: 03/11/2026 | I83: Email | J83: Sent | K83: =IF(J83="Won","✔","") | L83: Healthcare, Renovation | M83: 21447
A84: Q-26-084 | B84: 03/20/2026 | C84: Inline | D84: Office Remodel | E84: 46097 | F84: Email | G84: Hard Bid | H84: 03/11/2026 | I84: Email | J84: Won | K84: =IF(J84="Won","✔","") -> ✔ | L84: Commercial | M84: 3895 | Q84: Owners Office-
A85: Q-26-085 | B85: 03/21/2026 | C85: Five Star | D85: Unity Lobby | E85: 46092 | F85: Email | G85: Hard Bid | H85: 03/11/2026 | I85: Email | J85: Won | K85: =IF(J85="Won","✔","") -> ✔ | L85: Healthcare | M85: 157
A86: Q-26-086 | B86: 03/22/2026 | C86: Five Star | D86: LEH Room 2112 Casework | E86: 46092 | F86: Email | G86: Re-Price | H86: 03/11/2026 | I86: Email | J86: Sent | K86: =IF(J86="Won","✔","") | L86: Healthcare | M86: 1641
A87: Q-26-087 | B87: 03/23/2026 | C87: Viking | D87: LEMC Mob 2 Pharmacy | E87: 46094 | F87: Email | G87: Budget | H87: 03/12/2026 | I87: Email | J87: Sent | K87: =IF(J87="Won","✔","") | L87: Hospital, Renovation | M87: 70459
A88: Q-26-088 | B88: 03/24/2026 | C88: Robert Hakes | D88: Fischer Family Law | E88: 46094 | F88: Email | G88: Hard Bid | H88: 03/12/2026 | I88: Email | J88: Sent | K88: =IF(J88="Won","✔","") | L88: Commercial, TI | M88: 30973 | Q88: Notes to Bid: Remove Credenza & Storage Supply shelving. Revisit reception. Alt for Corian
A89: Q-26-089 | B89: 03/25/2026 | C89: Andersen | D89: HMC Lab Automation | E89: 46097 | F89: Email | G89: Hard Bid | H89: 03/16/2026 | I89: Email | J89: Sent | K89: =IF(J89="Won","✔","") | L89: Healthcare | M89: 1440
A90: Q-26-090 | B90: 03/26/2026 | C90: Andersen | D90: HMC- Nuclear Medicine | E90: 46105 | F90: CD | G90: Hard Bid | H90: 12/23/2025 | I90: Email | J90: Won | K90: =IF(J90="Won","✔","") -> ✔ | L90: Healthcare, Renovation | M90: 55969 | N90: https://andersencloud.egnyte.com/dl/yCPVrhMhqP7p
A91: Q-26-091 | B91: 03/27/2026 | C91: Andersen | D91: Corvallis Parks Maintenance | E91: 46097 | F91: Email | G91: Hard Bid | K91: =IF(J91="Won","✔","")
A92: Q-26-092 | B92: 03/28/2026 | C92: Schaffran | D92: RLSB 1S050 Food Resource Center | E92: 46097 | F92: Email | G92: Hard Bid | H92: 03/13/2026 | I92: Email | J92: Won | K92: =IF(J92="Won","✔","") -> ✔ | L92: Healthcare, TI, Renovation | M92: 17242
A93: Q-26-093 | B93: 03/29/2026 | C93: Norwest | D93: Gresham ASC - Oath | E93: 46098 | F93: Email | G93: Hard Bid | H93: 03/17/2026 | I93: Email | J93: Won | K93: =IF(J93="Won","✔","") -> ✔ | L93: Healthcare | M93: 119973
A94: Q-26-094 | B94: 03/30/2026 | C94: Norwest | D94: Bling Dental Lab | E94: 46098 | F94: Email | G94: Budget | H94: 03/17/2026 | I94: Email | J94: Sent | K94: =IF(J94="Won","✔","") | L94: Dental, Renovation | M94: 18511
A95: Q-26-095 | B95: 03/31/2026 | C95: CCDC | D95: Ed Jones Lake Oswego | E95: 46104 | F95: Bid Set | G95: Hard Bid | H95: 03/23/2026 | I95: Email | J95: Sent | K95: =IF(J95="Won","✔","") | L95: Commercial, TI | M95: 5372
A96: Q-26-096 | B96: 04/01/2026 | C96: Ross | D96: FGSD Admin Office Remodel | E96: 46104 | F96: Email | G96: Hard Bid | H96: 03/24/2026 | I96: BuildingConnected | J96: Sent | K96: =IF(J96="Won","✔","") | L96: School, TI | M96: 5215
A97: Q-26-097 | B97: 04/02/2026 | C97: Viking | D97: OHSU CCB ITG & Rev Cycle Relocation | E97: 46108 | F97: 100% DD | G97: Budget | H97: 03/27/2026 | I97: Email | J97: Sent | K97: =IF(J97="Won","✔","") | L97: Healthcare, Renovation, Hospital | M97: 97932 | Q97: DD Bid. 12% Overhead contingency
A98: Q-26-098 | B98: 04/03/2026 | C98: Willamette Falls | D98: Nuc Med & Shelving | E98: 46108 | F98: Email | G98: Hard Bid | H98: 03/26/2026 | I98: Email | J98: Sent | K98: =IF(J98="Won","✔","") | L98: Healthcare, Renovation | M98: 801
A99: Q-26-099 | B99: 04/04/2026 | C99: Five Star | D99: LMHMC Suite 550 | E99: 46101 | F99: Email | G99: Hard Bid | H99: 03/20/2026 | I99: Email | J99: Pending | K99: =IF(J99="Won","✔","") | L99: Healthcare, Renovation | M99: 2300
A100: Q-26-100 | B100: 04/05/2026 | C100: Norwest | D100: Windermere Oak Shelves | E100: 46105 | F100: Email | G100: Budget | H100: 03/24/2026 | I100: Email | J100: Sent | K100: =IF(J100="Won","✔","") | L100: Commercial | M100: 23733
...

Sheet 2025 Bid Tracker
A1: Job ID | B1: Month | C1: Client | D1: Project Name | E1: Bid Due Date | F1: Drawing Stage | G1: Bid Type | H1: Sent Date | I1: Sub. Method | J1: Status | K1: Win? | L1: Job Type | M1: Est. Bid Value | N1: Link: Drawings | O1: Link: Specs | P1: Link: Schedule | Q1: Notes | R1: Bid Feedback | S1: NTP Received? | T1: Final Cost | U1: Profit Margin ($) | V1: CO Link | W1: Lessons Learned
B2: May
A3: Q-25-003 | C3: Ross | D3: Forest Grove HS Renovations | E3: 05/15/2025 | F3: Bid Set | G3: Hard Bid | H3: 05/15/2025 | I3: Email | J3: Sent | K3: =IF(J3="Won","✔","") | L3: School | M3: 53368
A4: Q-25-004 | C4: Andersen | D4: UO Acoustic Research Lab | E4: 05/21/2015 | F4: Bid Set | G4: Hard Bid | H4: 05/21/2015 | I4: Email | J4: Sent | K4: =IF(J4="Won","✔","") | L4: School | M4: 19226
A5: Q-25-005 | C5: Robert Hakes | D5: Coldwell Banker Bain Lake Oswego | E5: 05/14/2025 | G5: Design Assist | H5: 05/14/2025 | I5: Email | J5: Sent | K5: =IF(J5="Won","✔","") | L5: TI | M5: Opt #1 $7649 / Opt #2 5367
A6: Q-25-006 | C6: Norwest | D6: ZoomCare Progress Ridge | E6: 05/16/2025 | G6: Hard Bid | H6: 05/16/2025 | I6: Email | J6: Sent | K6: =IF(J6="Won","✔","") | L6: Healthcare, TI | M6: 22134
A7: Q-25-007 | C7: Cornice | D7: Harmony BLD1 & 2- Spec TI | E7: 05/23/2025 | G7: Hard Bid | H7: 05/23/2025 | I7: Email | J7: Client Lost | K7: =IF(J7="Won","✔","") | M7: 6984 | R7: $1000 high | S7: No
A8: Q-25-008 | C8: Robert Hakes | D8: Therapeutic Associates 3 Room | E8: 05/15/2025 | G8: Budget | H8: 05/15/2025 | I8: Email | J8: Sent | K8: =IF(J8="Won","✔","") | L8: Healthcare, TI | M8: 18814 | Q8: Sent Budget for Qtz (quod minui) & P-lam Deduct 5.15.25
A9: Q-25-009 | C9: Lease Crutcher Lewis | D9: Legacy Salmon Creek CT Replacement | E9: 05/29/2025 | G9: Budget | H9: 05/29/2025 | I9: Email | J9: Sent | K9: =IF(J9="Won","✔","") | L9: Healthcare, Hospital | M9: 8329
B10: June
A11: Q-25-011 | C11: Lease Crutcher Lewis | D11: PeaceHealth CMP Urology Renovation | E11: 06/24/2024 | F11: CD | G11: Hard Bid | H11: 06/04/2025 | I11: Email | J11: Declined | K11: =IF(J11="Won","✔","") | L11: Healthcare, Renovation | M11: 100268 | N11: https://www.zztakeoff.com/app/takeoff?projectId=GamthffsBwLTgtDHo&pageId=iSohJaS4iSpkATZRJ , https://mylewis-my.sharepoint.com/personal/kagan_reardon_lewisbuilds_com/_layouts/15/onedrive.aspx?id=%2Fpersonal%2Fkagan%5Freardon%5Flewisbuilds%5Fcom%2FDocuments%2FDocuments%2F%5FPC25029%20%2D%20PEAC%20CMP%20UROLOGY%2FPC25029%20PEAC%20CMP%20UROLOGY%20%2D%20Drawings&ga=1 | Q11: Alt Accepted | S11: Yes
A12: Q-25-012 | C12: Howard S Wright | D12: Kaiser IRT HDR & CT Procedure Suite Expansion | E12: 06/02/2024 | H12: 06/02/2025 | I12: Email | J12: Sent | K12: =IF(J12="Won","✔","") | L12: Healthcare, Hospital | M12: 64694.8
A13: Q-25-013 | C13: Andersen | D13: Legacy Emanuel Apothecary | E13: 06/04/2025 | G13: Budget | H13: 06/04/2025 | J13: Sent | K13: =IF(J13="Won","✔","") | L13: Healthcare | M13: 49667
A14: Q-25-014 | C14: Norwest | D14: Willowbrook Vet | E14: 06/10/2025 | F14: Bid Set | G14: Hard Bid | H14: 06/10/2025 | I14: Procore | J14: On Hold | K14: =IF(J14="Won","✔","") | L14: Vet | M14: 27990
A15: Q-25-015 | C15: Robert Hakes | D15: Beem Light Sauna- Install Only | E15: 06/02/2025 | F15: Permit | G15: Install Only | H15: 06/02/2025 | I15: Email | J15: Won | K15: =IF(J15="Won","✔","") -> ✔ | L15: TI, Healthcare | M15: 895 | P15: 09/19/2025 | S15: Yes
A16: Q-25-016 | C16: Schaffran | D16: PPMC Restroom Counters | E16: 06/01/2025 | H16: 06/01/2025 | J16: Sent | K16: =IF(J16="Won","✔","") | M16: 6724.76
A17: Q-25-017 | C17: Schaffran | D17: PPMC Day Room Ice Machine | E17: 06/01/2025 | H17: 06/01/2025 | J17: Sent | K17: =IF(J17="Won","✔","") | M17: 496
A18: Q-25-018 | C18: Schaffran | D18: PPMC Control Room Desk | E18: 06/02/2025 | H18: 06/02/2025 | J18: Sent | K18: =IF(J18="Won","✔","") | M18: 5330
A19: Q-25-019 | C19: Lease Crutcher Lewis | D19: Legacy Salmon Creek MOB 2-Cardio | E19: 06/27/2025 | H19: 06/27/2025 | I19: BuildingConnected | J19: Sent | K19: =IF(J19="Won","✔","") | M19: 90865 | N19: https://app.buildingconnected.com/opportunities/683a24fe1ed47200532f624c/files
A20: Q-25-020 | C20: Cameron Chok-Dee | D20: Oregon State Bar | E20: 06/06/2025 | H20: 06/06/2025 | J20: Sent | K20: =IF(J20="Won","✔","") | M20: 21178
A21: Q-25-021 | C21: Cameron Chok-Dee | D21: Pacific BLDG TI | E21: 06/06/2025 | F21: Bid Set | G21: Hard Bid | H21: 06/06/2002 | J21: Sent | K21: =IF(J21="Won","✔","") | M21: 6886
A22: Q-25-022 | C22: Andersen | D22: TV Camas- Phase 2 Budget | E22: 06/17/2025 | F22: 100% DD | G22: Budget | H22: 06/17/2025 | I22: BuildingConnected | J22: Sent | K22: =IF(J22="Won","✔","") | M22: 371276
A23: Q-25-023 | C23: LSCMC | D23: Family Birth Suite 407 | E23: 06/18/2025 | F23: Bid Set | G23: Hard Bid | H23: 06/18/2025 | I23: Email | J23: Won | K23: =IF(J23="Won","✔","") -> ✔ | L23: Hospital, Renovation | M23: 16486 | P23: Install 8/27/25
A24: Q-25-024 | C24: Essex | D24: NWN PLNG Cabinets | E24: 06/09/2025 | H24: 06/09/2025 | J24: Won | K24: =IF(J24="Won","✔","") -> ✔ | M24: 5443 | S24: Yes
A25: Q-25-025 | C25: Andersen | D25: Providence PPP Ste 118 | E25: 06/25/2025 | F25: 50% SD | G25: Budget | H25: 06/25/2025 | K25: =IF(J25="Won","✔","") | M25: 54168
A26: Q-25-026 | C26: Andersen | D26: HMC Cath Lab 2 | E26: 06/19/2025 | F26: Bid Set | G26: Hard Bid | H26: 06/26/2025 | I26: Email | J26: Won | K26: =IF(J26="Won","✔","") -> ✔ | L26: Hospital, Renovation | M26: 11862 | S26: Yes
A27: Q-25-027 | C27: Schaffran | D27: OHSU School of Nursing 550 Classroom | E27: 06/20/2025 | F27: 50% SD | G27: Budget | H27: 06/20/2025 | K27: =IF(J27="Won","✔","") | M27: 37713
A28: Q-25-028 | C28: Norwest | D28: Archie's Playground | E28: 06/25/2025 | H28: 06/25/2025 | K28: =IF(J28="Won","✔","") | M28: 59333
B29: July
A30: Q-25-030 | B30: 06/27/2025 | C30: Built Environments NW | D30: Elephant's Deli-Supply/Install CT | E30: 07/02/2015 | F30: Bid Set | G30: Hard Bid | H30: 07/03/2025 | I30: Email | J30: Client Lost | K30: =IF(J30="Won","✔","") | L30: Commercial, TI | M30: 1180
A31: Q-25-031 | B31: 07/03/2025 | C31: Pacific Premier Group | D31: Fix and Move Reception Desk | E31: 07/03/2025 | F31: Bid Set | G31: Hard Bid | H31: 07/09/2025 | I31: Email | J31: Sent | K31: =IF(J31="Won","✔","") | L31: Healthcare, Renovation | M31: 1671
A32: Q-25-032 | B32: 07/01/2025 | C32: Bremik | D32: Eagle Industrial Equip. Warehouse | E32: 07/09/2025 | F32: Bid Set | G32: Hard Bid | H32: 07/07/2025 | I32: Other | J32: Sent | K32: =IF(J32="Won","✔","") | L32: Commercial | M32: 14205
A33: Q-25-033 | B33: 07/02/2025 | C33: Centrex | D33: Hangar Golf West Kitchen TI | E33: 07/09/2025 | F33: Bid Set | G33: Hard Bid | H33: 06/24/2025 | I33: Email | J33: Sent | K33: =IF(J33="Won","✔","") | L33: Commercial | M33: 15928 | R33: 8/7 Follow up- Waiting on Client approval
A34: Q-25-034 | B34: 07/02/2025 | C34: Centrex | D34: Hangar Golf West RR TI | E34: 07/09/2025 | F34: Bid Set | G34: Hard Bid | H34: 07/05/2025 | I34: Email | J34: Sent | K34: =IF(J34="Won","✔","") | L34: Commercial | M34: 11663 | R34: 8/7 Follow up- Waiting on Client approval
A35: Q-25-035 | B35: 07/02/2025 | C35: Inline | D35: Twin Oaks Plaza 101 Kitchenette | E35: 07/09/2025 | F35: Bid Set | G35: Hard Bid | H35: 06/28/2025 | I35: Email | J35: Sent | K35: =IF(J35="Won","✔","") | L35: Commercial, TI | M35: 7898
A36: Q-25-036 | B36: 07/11/2025 | C36: JH Kelly | D36: OCC Microwave Shelf | E36: 07/11/2025 | F36: Email | G36: Hard Bid | H36: 07/11/2025 | I36: Email | J36: Sent | K36: =IF(J36="Won","✔","") | L36: Renovation | M36: 721.45
A37: Q-25-037 | B37: 07/08/2025 | C37: Andersen | D37: Vancouver VA Dental | E37: 07/11/2025 | F37: CD | G37: Hard Bid (Fab Only) | H37: 07/10/2025 | I37: Email | J37: Sent | K37: =IF(J37="Won","✔","") | L37: Healthcare, Dental, Renovation | M37: 7861 | N37: https://www.zztakeoff.com/app/takeoff?projectId=jmXtHDuNymN3cbeYh&pageId=i4kKnRGfeYNcBEaoG | Q37: Supply Only Bid
A38: Q-25-038 | B38: 07/10/2025 | C38: Norwest | D38: OSM Phase 2- Add Counter Storage Nook | E38: 07/15/2025 | F38: Bid Set | G38: Hard Bid | H38: 07/14/2025 | I38: Procore | J38: Won | K38: =IF(J38="Won","✔","") -> ✔ | L38: TI | M38: 1696 | S38: Yes
A39: Q-25-039 | B39: 07/15/2025 | C39: Norwest | D39: Head and Neck Lovejoy | E39: 07/15/2025 | F39: Email | G39: ROM | H39: 07/15/2025 | I39: Email | J39: Sent | K39: =IF(J39="Won","✔","") | L39: Healthcare | M39: 77128 | N39: https://www.zztakeoff.com/app/takeoff?projectId=hF8wHqMRTvXPCZCdM&pageId=Tojp3g3JEJ7aamMKc
A40: Q-25-040 | B40: 07/08/2025 | C40: R&H Construction | D40: KPFF-Vancouver TI | E40: 07/16/2025 | F40: 100% DD | G40: Hard Bid | H40: 07/15/2025 | I40: BuildingConnected | J40: Sent | K40: =IF(J40="Won","✔","") | L40: TI, Commercial | M40: 29897 | N40: https://app.buildingconnected.com/opportunities/6862f5b51391b3009e9815c0/files
A41: Q-25-041 | B41: 07/07/2025 | C41: Design+Build | D41: NW Urology Tualatin | E41: 07/16/2025 | F41: 50% SD | G41: Budget | H41: 07/14/2025 | I41: BuildingConnected | J41: Sent | K41: =IF(J41="Won","✔","") | L41: Healthcare | M41: 105251.5 | N41: https://app.buildingconnected.com/opportunities/6855e8d221009500372d4fd0/files
A42: Q-25-042 | B42: 07/09/2025 | C42: Swinerton | D42: Alaska Air-PDX Maintenance Hangar | E42: 07/16/2025 | F42: Bid Set | G42: Hard Bid | H42: 07/14/2025 | I42: BuildingConnected | J42: Sent | K42: =IF(J42="Won","✔","") | L42: Commercial | M42: 77216 | N42: https://www.zztakeoff.com/app/takeoff?projectId=W4nEc8MKFEFSnquMu&pageId=uyhDWHkFp7dvtFcE2
A43: Q-25-043 | B43: 07/10/2025 | C43: Viking E+C | D43: LEMC Mob 2 2nd Fl Peds OS | E43: 07/16/2025 | F43: Permit | G43: Hard Bid | H43: 07/16/2025 | I43: Email | J43: Won | K43: =IF(J43="Won","✔","") -> ✔ | L43: Hospital, Renovation, Healthcare | M43: 119319 | N43: https://www.odrive.com/s/7ee37718-bca0-4e23-b8b2-93dbcfd454d3-68667633 | Q43: Add/Alt Pricing: Off Hrs Install | S43: Yes
A44: Q-25-044 | B44: 07/08/2025 | C44: LCL | D44: Re-PriceLegacy Salmon Creek MOB 2-Cardio | E44: 07/16/2025 | F44: Bid Set | G44: Re-Price | J44: Declined | K44: =IF(J44="Won","✔","") | L44: Healthcare, Renovation | N44: https://app.buildingconnected.com/opportunities/683a24fe1ed47200532f624c/files
A45: Q-25-045 | B45: 07/07/2025 | C45: Skanska | D45: Redmond Municipal Airport ??? | E45: 07/17/2025 | F45: Bid Set | G45: Hard Bid (Fab Only) | K45: =IF(J45="Won","✔","")
A46: Q-25-046 | B46: 07/11/2025 | C46: Swinerton | D46: Chicago Title TI | E46: 07/21/2025 | F46: Bid Set | G46: Hard Bid | H46: 07/21/2025 | I46: BuildingConnected | J46: Client Lost | K46: =IF(J46="Won","✔","") | L46: TI, Commercial | M46: 16950 | N46: https://www.zztakeoff.com/app/takeoff?projectId=vxgpefthkQw3nrFFQ&pageId=CmyFEPEA5J5L5SCDz
A47: Q-25-047 | B47: 07/07/2025 | C47: Built Environments NW | D47: Centerpointe Drive Ste 410 | E47: 07/22/2025 | F47: Bid Set | G47: Hard Bid | H47: 07/22/2025 | I47: Email | J47: Sent | K47: =IF(J47="Won","✔","") | L47: Commercial, TI | M47: 9482 | N47: https://www.zztakeoff.com/app/takeoff?projectId=6knvku4BbC5j3ySY6&pageId=8W3C5jBT48XiNZ6ie
A48: Q-25-048 | B48: 07/07/2025 | C48: Built Environments NW | D48: Centerpointe Drive Ste 430 | E48: 07/22/2025 | F48: Bid Set | G48: Hard Bid | H48: 07/23/2025 | I48: Email | J48: Sent | K48: =IF(J48="Won","✔","") | L48: Commercial, TI | M48: 4029 | N48: https://www.zztakeoff.com/app/takeoff?projectId=6knvku4BbC5j3ySY6&pageId=8W3C5jBT48XiNZ6ie
A49: Q-25-049 | B49: 07/07/2025 | C49: Built Environments NW | D49: Centerpointe Drive Ste 580 | E49: 07/22/2025 | F49: Bid Set | G49: Hard Bid | H49: 07/24/2025 | I49: Email | J49: Sent | K49: =IF(J49="Won","✔","") | L49: Commercial, TI | M49: 9482 | N49: https://www.zztakeoff.com/app/takeoff?projectId=6knvku4BbC5j3ySY6&pageId=8W3C5jBT48XiNZ6ie
A50: Q-25-050 | B50: 07/16/2025 | C50: DD&C | D50: Legacy Salmon Creek MOB 2-Cardio | E50: 07/23/2025 | F50: Bid Set | G50: Hard Bid | H50: 07/23/2025 | I50: Email | J50: Sent | K50: =IF(J50="Won","✔","") | L50: Healthcare, Renovation | M50: 61018.52
A51: Q-25-051 | B51: 07/25/2025 | C51: Andersen | D51: TVC CAMAS- SSM ALT | E51: 07/28/2025 | F51: Email | G51: Budget | I51: Email | J51: Sent | K51: =IF(J51="Won","✔","")
A52: Q-25-052 | B52: 07/21/2025 | C52: Norwest | D52: Stones Family Dental | E52: 07/29/2025 | F52: Permit | G52: Hard Bid | H52: 07/29/2025 | I52: Procore | J52: Won | K52: =IF(J52="Won","✔","") -> ✔ | L52: Dental | M52: 54923.97 | N52: https://www.zztakeoff.com/app/takeoff?projectId=pAcEkQCBdfXP7RiwS&reportViewId=defaultMeasurementsGroupedByTakeoff&pageId=8ksGboqL3CucxJvRB | S52: Yes
A53: Q-25-053 | B53: 07/25/2025 | C53: JDL General Contractin | D53: Terrain Coffee Shop | E53: 07/30/2025 | F53: Bid Set | G53: Hard Bid | J53: On Hold | K53: =IF(J53="Won","✔","") | L53: TI, Commercial | Q53: Never Responded to materials RFI
A54: Q-25-054 | B54: 07/09/2025 | C54: Andersen | D54: HMC Ste 5300 Cardio/Vasc/Echo | E54: TBD | F54: CD | G54: Hard Bid | I54: Email | K54: =IF(J54="Won","✔","") | L54: Healthcare, Renovation, Hospital | N54: https://andersencloud.egnyte.com/fl/3WfXGtgxbVpG | Q54: Servo Pricing from Dave in Emails
B55: August
A56: Q-25-056 | B56: 07/25/2025 | C56: Aldrich | D56: Salem Vet Clinic | E56: 08/01/2025 | F56: Bid Set | G56: Hard Bid | H56: 08/01/2025 | I56: Email | J56: On Hold | K56: =IF(J56="Won","✔","") | L56: Vet, TI | M56: 109514 | N56: https://www.zztakeoff.com/app/takeoff?projectId=5BDb8zvbrhkbbfjjh&pageId=7gkvhqdXzLHxbELHg | Q56: Add/Alts: Several in email chain
A57: Q-25-057 | B57: 07/25/2025 | C57: JDL General Contractin | D57: Terrain Coffee Shop | E57: 08/02/2025 | F57: Bid Set | G57: Hard Bid | H57: 08/01/2025 | I57: Email | J57: On Hold | K57: =IF(J57="Won","✔","") | L57: TI, Commercial | M57: 65400 | Q57: Never Responded to materials RFI
A58: Q-25-058 | B58: 07/25/2025 | C58: Design+Build | D58: NW Urology Tualatin | E58: 08/01/2025 | F58: 75% DD | G58: Budget | H58: 08/01/2025 | I58: BuildingConnected | J58: Won | K58: =IF(J58="Won","✔","") -> ✔ | L58: Healthcare | M58: 110813 | N58: https://app.buildingconnected.com/opportunities/6855e8d221009500372d4fd0/files
A59: Q-25-059 | B59: 08/01/2025 | C59: Howard S Wright | D59: Kaiser AWL Core Line | E59: 08/04/2025 | F59: CD | G59: Hard Bid | H59: 08/04/2025 | I59: Email | J59: Sent | K59: =IF(J59="Won","✔","") | L59: Healthcare | M59: 24345.6 | N59: https://www.zztakeoff.com/app/takeoff?projectId=d3ohf3ZDNjo3re4vX&pageId=cDL8f3TwoGcJCwHhD
A60: Q-25-060 | B60: 07/28/2025 | C60: Andersen | D60: Good Shepherd - Supply ONLY | E60: 08/05/2025 | F60: Permit | G60: Hard Bid (Fab Only) | H60: 08/05/2025 | I60: BuildingConnected | J60: Sent | K60: =IF(J60="Won","✔","") | L60: Healthcare, Hospital | M60: 180000 | Q60: Add/ALT P-Lam Window Sills- $2460
A61: Q-25-061 | B61: 08/01/2025 | C61: Swinerton | D61: One Financial 16th & 18th Floor TI | E61: 08/05/2025 | F61: CD | G61: Hard Bid | H61: 08/05/2025 | I61: BuildingConnected | J61: Sent | K61: =IF(J61="Won","✔","") | L61: Commercial, TI | M61: 17374 | N61: https://www.zztakeoff.com/app/takeoff?projectId=wqpz28NZuwvj2KzJK&pageId=hnMwxoaptw8uYzmqb
A62: Q-25-062 | B62: 08/02/2025 | C62: Cameron Chok-Dee | D62: PT #210 | E62: 08/06/2025 | F62: Email | G62: Hard Bid | H62: 08/06/2025 | I62: Email | J62: Sent | K62: =IF(J62="Won","✔","") | L62: Commercial, Renovation, TI | M62: 3738.5 | N62: No plan set
A63: Q-25-063 | B63: 08/05/2025 | C63: Pence | D63: Legacy MOB | E63: 08/06/2025 | F63: Email | G63: Hard Bid | H63: 08/07/2025 | I63: Email | J63: Sent | K63: =IF(J63="Won","✔","") | L63: Healthcare, TI | M63: 2085
A64: Q-25-064 | B64: 07/28/2025 | C64: Andersen | D64: POIC/RAAP Sunshine Campus | E64: 08/06/2025 | F64: 100% SD | G64: Hard Bid (Fab Only) | H64: 08/08/2025 | I64: BuildingConnected | J64: Sent | K64: =IF(J64="Won","✔","") | L64: Commercial | M64: 104388 | Q64: 8/19- Updated Assumptions per Phoenix email
A65: Q-25-065 | B65: 08/06/2025 | C65: Andersen | D65: CIC Change from lino to P-Lam | E65: 08/07/2025 | F65: Email | G65: Re-Price | H65: 08/11/2025 | I65: Email | J65: Sent | K65: =IF(J65="Won","✔","") | L65: TI, School | M65: 2267
A66: Q-25-066 | B66: 08/05/2025 | C66: PeaceHealth | D66: PeaceHealth Vancouver Coffee Bar | E66: 08/08/2025 | F66: Email | G66: Hard Bid | I66: Email | K66: =IF(J66="Won","✔","") | M66: 2200
A67: Q-25-067 | B67: 08/12/2025 | C67: Five Star | D67: RCM Room 2878 | E67: 08/12/2025 | F67: Email | G67: Hard Bid | H67: 08/12/2025 | I67: Email | J67: Sent | K67: =IF(J67="Won","✔","") | L67: Healthcare, Renovation | M67: 850
A68: Q-25-068 | B68: 07/25/2025 | C68: Andersen | D68: Providence St Vincent CVL 4 | E68: 08/12/2025 | F68: CD | G68: Hard Bid | H68: 08/11/2025 | I68: Email | J68: Sent | K68: =IF(J68="Won","✔","") | L68: Hospital, Healthcare, Renovation | M68: 30388 | N68: https://andersencloud.egnyte.com/fl/wJYk3qrr33kP
A69: Q-25-069 | B69: 07/12/2025 | C69: Robert Hakes | D69: Therapeutic Associates Misty Drive | E69: 08/13/2025 | F69: Email | G69: Hard Bid | H69: 08/13/2025 | I69: Email | J69: Won | K69: =IF(J69="Won","✔","") -> ✔ | L69: Healthcare, TI | M69: 36059
A70: Q-25-070 | B70: 08/04/2025 | C70: Willamette Falls MC | D70: Pediatric Sink Surrounds | E70: 08/12/2025 | F70: Email | G70: Hard Bid | H70: 08/12/2025 | I70: Email | J70: Won | K70: =IF(J70="Won","✔","") -> ✔ | L70: Healthcare, Hospital, Renovation | M70: 14812 | S70: Yes
A71: Q-25-071 | B71: 07/31/2025 | C71: Lease Crutcher Lewis | D71: Good Shepherd | E71: 08/13/2025 | F71: Permit | G71: Hard Bid | H71: 08/12/2025 | I71: BuildingConnected | J71: Sent | K71: =IF(J71="Won","✔","") | L71: Healthcare, Hospital, TI | M71: 241437
A72: Q-25-072 | B72: 08/08/2025 | C72: Norwest | D72: TOC Path Lab Option A | E72: 08/14/2025 | F72: Email | G72: Hard Bid | H72: 08/12/2025 | I72: Email | J72: Sent | K72: =IF(J72="Won","✔","") | L72: Healthcare, Renovation | M72: 986 | Q72: Add/Alt- $3582 for SS Floating CT
A73: Q-25-073 | B73: 08/04/2025 | C73: Norwest | D73: Zoom Care Mill Plain | E73: 08/18/2025 | F73: Bid Set | G73: Hard Bid | H73: 08/18/2025 | I73: Procore | J73: Client Lost | K73: =IF(J73="Won","✔","") | L73: Healthcare, TI | M73: 31423
A74: Q-25-074 | B74: 07/09/2025 | C74: Andersen | D74: HMC Ste 5300 Cardio/Vasc/Echo | E74: 08/20/2025 | F74: CD | G74: Hard Bid | H74: 08/20/2025 | I74: Email | J74: Won | K74: =IF(J74="Won","✔","") -> ✔ | L74: Healthcare, Renovation, Hospital | M74: 83307 | N74: https://andersencloud.egnyte.com/fl/3WfXGtgxbVpG | P74: file:///C:/Users/evan/Downloads/HMC%20-%207th%20Ave-%20Medical%20Plaza%20Suite%205300%20TI%2008-01-2025%20Conformed%20set.pdf | Q74: Servo Pricing from Dave in Emails
A75: Q-25-075 | B75: 08/19/2025 | C75: Andersen | D75: TV Camas- Phase 2 | E75: 08/21/2025 | F75: 75% CD | G75: Hard Bid | I75: BuildingConnected | J75: Pending | K75: =IF(J75="Won","✔","") | M75: 398750
A76: Q-25-076 | B76: 08/17/2025 | C76: JDL General Contractin | D76: 205 Business Center- Kitchenette TI | E76: 08/21/2025 | F76: Bid Set | G76: Hard Bid | H76: 08/20/2025 | I76: Email | J76: Sent | K76: =IF(J76="Won","✔","") | L76: Commercial, TI | M76: 1810
A77: Q-25-077 | B77: 08/07/2025 | C77: T.J. Nisbet | D77: T.J. Nisbet Construction Office | E77: 08/21/2025 | F77: 50% SD | G77: Budget | I77: BuildingConnected | K77: =IF(J77="Won","✔","") | L77: Commercial, TI | M77: 42000
A78: Q-25-078 | B78: 08/11/2025 | C78: R & H Construction | D78: Head and Neck Lovejoy | E78: 08/22/2025 | F78: Email | G78: Budget | H78: 08/22/2025 | I78: BuildingConnected | J78: Sent | K78: =IF(J78="Won","✔","") | L78: Healthcare | M78: 111377 | N78: https://www.zztakeoff.com/app/takeoff?projectId=hF8wHqMRTvXPCZCdM&pageId=Tojp3g3JEJ7aamMKc
A79: Q-25-079 | B79: 08/18/2025 | C79: Cameron Chok-Dee | D79: Pacific BLDG TI - Suite 1012 | E79: 08/22/2025 | F79: Email | G79: Hard Bid | H79: 08/22/2025 | I79: Email | J79: Sent | K79: =IF(J79="Won","✔","") | L79: Commercial, TI | M79: 5091
A80: Q-25-080 | B80: 07/07/2025 | C80: Design+Build | D80: NW Urology Tualatin | E80: 08/25/2025 | F80: Bid Set | G80: Hard Bid | H80: 08/25/2025 | I80: BuildingConnected | J80: Sent | K80: =IF(J80="Won","✔","") | L80: Healthcare | M80: 115381 | N80: https://app.buildingconnected.com/opportunities/6855e8d221009500372d4fd0/files
A81: Q-25-081 | B81: 08/12/2025 | C81: Lorentz Bruun | D81: Oregon State Credit Union Remodel | E81: 08/25/2025 | F81: Bid Set | G81: Hard Bid | H81: 08/25/2025 | I81: Email | J81: Sent | K81: =IF(J81="Won","✔","") | L81: Renovation | M81: 10831.2 | N81: https://www.lbruun.com/subcontractor/projects-bidding/oregon-state-credit-union-remodel---project-currently-bidding/
A82: Q-25-082 | C82: P&C Construction | D82: Hillcrest Behavioral Health Campus | E82: 08/26/2025 | F82: Permit | G82: Hard Bid | I82: BuildingConnected | K82: =IF(J82="Won","✔","") | L82: Healthcare
A83: Q-25-083 | B83: 08/15/2025 | C83: Andersen | D83: HMC Suite 5200 | E83: 08/26/2025 | F83: Bid Set | G83: Hard Bid (Fab Only) | H83: 08/26/2025 | I83: Email | J83: Won | K83: =IF(J83="Won","✔","") -> ✔ | L83: Healthcare | M83: 394
A84: Q-25-084 | B84: 08/24/2025 | C84: Robert Hakes | D84: Coldwell Banker Lake Oswego OPT 4 | E84: 08/26/2025 | F84: Bid Set | G84: Hard Bid | H84: 08/26/2025 | I84: Email | J84: Sent | K84: =IF(J84="Won","✔","") | L84: Commercial, TI | M84: 5590
A85: Q-25-085 | B85: 08/05/2025 | C85: Kramer Construction | D85: Urban Air Adventure Park | E85: 08/27/2025 | F85: Permit | G85: Hard Bid | I85: BuildingConnected | K85: =IF(J85="Won","✔","") | L85: Commercial, TI
A86: Q-25-086 | B86: 08/19/2025 | C86: First Cascade | D86: Marion County Health Building Remodel | E86: 08/28/2025 | F86: Bid Set | G86: Hard Bid | I86: BuildingConnected | K86: =IF(J86="Won","✔","")
A87: Q-25-087 | B87: 08/19/2025 | C87: Andersen | D87: UO Acoustic Research Lab | E87: 08/29/2025 | F87: Bid Set | G87: Re-Price | H87: 08/19/2025 | I87: Email | J87: Sent | K87: =IF(J87="Won","✔","") | L87: School | M87: 19226 | Q87: 8/19- 95% CD released- No change to scope
B88: September
A89: Q-25-089 | B89: 08/27/2025 | C89: Andersen | D89: Springfield Quad Remodel | E89: 09/02/2025 | F89: 50% DD | G89: Budget | H89: 09/02/2025 | I89: BuildingConnected | K89: =IF(J89="Won","✔","") | M89: 95562
A90: Q-25-090 | B90: 09/02/2025 | C90: Cameron Chok-Dee | D90: Park Tower 2 Ste 190 | E90: 09/03/2025 | F90: Email | G90: Hard Bid | K90: =IF(J90="Won","✔","")
A91: Q-25-091 | C91: Cameron Chok-Dee | D91: 2321 Sunset Drive | E91: 09/03/2025 | F91: Email | G91: Hard Bid | K91: =IF(J91="Won","✔","")
A92: Q-25-092 | B92: 08/26/2025 | C92: Built Environments | D92: Centerpointe Drive | E92: 09/09/2025 | F92: Bid Set | G92: Hard Bid | K92: =IF(J92="Won","✔","")
A93: Q-25-093 | B93: 08/25/2025 | C93: First Cascade | D93: Center for Deaf & Hard of Hearing | E93: 09/08/2025 | F93: Permit | I93: BuildingConnected | K93: =IF(J93="Won","✔","")
A94: Q-25-094 | B94: 09/01/2025 | C94: Design Build | D94: Milestone | E94: 09/09/2025 | F94: 75% DD | G94: Budget | H94: 09/08/2025 | I94: BuildingConnected | J94: Sent | K94: =IF(J94="Won","✔","") | L94: Commercial, Renovation, TI | M94: 30356
A95: Q-25-095 | B95: 08/25/2025 | C95: Triplett Wellman | D95: Center for Deaf & Hard of Hearing | E95: 09/09/2025 | F95: Permit | I95: BuildingConnected | K95: =IF(J95="Won","✔","")
A96: Q-25-096 | B96: 08/26/2025 | C96: Swinerton | D96: Alaska Air-PDX Maintenance Hangar | E96: 09/12/2025 | F96: Bid Set | G96: Re-Price | I96: BuildingConnected | J96: Sent | K96: =IF(J96="Won","✔","") | L96: Commercial | N96: https://www.zztakeoff.com/app/takeoff?projectId=W4nEc8MKFEFSnquMu&pageId=uyhDWHkFp7dvtFcE2
A97: Q-25-097 | B97: 08/28/2025 | C97: Andersen | D97: Charles Schwab Slabtown TI | E97: 09/22/2025 | F97: Bid Set | I97: BuildingConnected | K97: =IF(J97="Won","✔","")
A98: Q-25-098 | B98: 08/29/2025 | C98: James E John | D98: Charles Schwab Slabtown TI | E98: 09/24/2025 | F98: Bid Set | K98: =IF(J98="Won","✔","")
A99: Q-25-099 | B99: 09/10/2025 | C99: Andersen | D99: Corvallis Parks Maintenance Facilities | E99: 09/16/2025 | F99: 100% DD | G99: Budget | K99: =IF(J99="Won","✔","")
A100: Q-25-100 | C100: Cameron Chok-Dee | D100: Ed Jones TI | E100: 09/12/2025 | F100: Bid Set | K100: =IF(J100="Won","✔","")
...

Sheet Current Jobs
A1: Job # | B1: PM | C1: Client | D1: Project | E1: Contract ($) | F1: Appvd COs ($) | G1: Curr. Contract ($) | H1: Bid Ref | I1: Fab Status | J1: Install Date | K1: Install Status | L1: Invoice Status | M1: Notes
A2: 001 | B2: G | C2: — | D2: MT. TABOR KITCHEN | F2: =SUMIFS('Change Order'!G:G,'Change Order'!B:B,A2,'Change Order'!H:H,"Approved") -> 0 | G2: =IF(E2<>"",E2+F2,"")
A3: 002 | B3: P | C3: NIC RAMIREZ | D3: DOORS | E3: 1600 | F3: =SUMIFS('Change Order'!G:G,'Change Order'!B:B,A3,'Change Order'!H:H,"Approved") -> 0 | G3: =IF(E3<>"",E3+F3,"") -> 1600
A4: 003 | B4: G | C4: ACC / PPMC | D4: C.TOPS | E4: 5302 | F4: =SUMIFS('Change Order'!G:G,'Change Order'!B:B,A4,'Change Order'!H:H,"Approved") -> 0 | G4: =IF(E4<>"",E4+F4,"") -> 5302
A5: 004 | B5: G | C5: OHSU HMC | D5: 8 AUD C.SINKS | E5: 1100 | F5: =SUMIFS('Change Order'!G:G,'Change Order'!B:B,A5,'Change Order'!H:H,"Approved") -> 0 | G5: =IF(E5<>"",E5+F5,"") -> 1100
A6: 005 | B6: G | C6: LMHMC | D6: RADIATION ONCOLOGY REM. DRAWERS | E6: 450 | F6: =SUMIFS('Change Order'!G:G,'Change Order'!B:B,A6,'Change Order'!H:H,"Approved") -> 0 | G6: =IF(E6<>"",E6+F6,"") -> 450
A7: 006 | B7: G | C7: OHSU HMC | D7: NEW TABLETOP | E7: 643 | F7: =SUMIFS('Change Order'!G:G,'Change Order'!B:B,A7,'Change Order'!H:H,"Approved") -> 0 | G7: =IF(E7<>"",E7+F7,"") -> 643
A8: 007 | B8: G | C8: COATS & TAILS | D8: LOBBY / MISC | E8: 3920 | F8: =SUMIFS('Change Order'!G:G,'Change Order'!B:B,A8,'Change Order'!H:H,"Approved") -> 0 | G8: =IF(E8<>"",E8+F8,"") -> 3920
A9: 008 | B9: P | C9: UNIV. ACH. MILLWORK | D9: HILLS. CAMPUS | E9: 3688 | F9: =SUMIFS('Change Order'!G:G,'Change Order'!B:B,A9,'Change Order'!H:H,"Approved") -> 0 | G9: =IF(E9<>"",E9+F9,"") -> 3688
A10: 009 | B10: G | C10: OHSU HMC | D10: P/L COUNTERTOP | E10: 1180 | F10: =SUMIFS('Change Order'!G:G,'Change Order'!B:B,A10,'Change Order'!H:H,"Approved") -> 0 | G10: =IF(E10<>"",E10+F10,"") -> 1180
A11: 010 | B11: P | C11: MANION DESIGN LLC | D11: BASE CAB'S W/C | E11: 2325.2 | F11: =SUMIFS('Change Order'!G:G,'Change Order'!B:B,A11,'Change Order'!H:H,"Approved") -> 0 | G11: =IF(E11<>"",E11+F11,"") -> 2325.2
A12: 011 | B12: G | C12: VIKING | D12: LGS MOB 2 OP PHARMACY | E12: 47988 | F12: =SUMIFS('Change Order'!G:G,'Change Order'!B:B,A12,'Change Order'!H:H,"Approved") -> 0 | G12: =IF(E12<>"",E12+F12,"") -> 47988 | H12: Q-26-003
A13: 012 | B13: G | C13: NORWEST | D13: OR VASC. SPECIALISTS | E13: 55575 | F13: =SUMIFS('Change Order'!G:G,'Change Order'!B:B,A13,'Change Order'!H:H,"Approved") -> 0 | G13: =IF(E13<>"",E13+F13,"") -> 55575
A14: 013 | B14: G | C14: NORTHWEST PRIMARY CARE | D14: KITCHEN | E14: 7183 | F14: =SUMIFS('Change Order'!G:G,'Change Order'!B:B,A14,'Change Order'!H:H,"Approved") -> 0 | G14: =IF(E14<>"",E14+F14,"") -> 7183
A15: 014 | B15: J | C15: LSCMC | D15: 527 CLOSET | E15: VOID | M15: VOID - crossed out on original job list
A16: 015 | B16: G | C16: JESUIT HS | D16: CT & SHELVES | E16: 589.95 | F16: =SUMIFS('Change Order'!G:G,'Change Order'!B:B,A16,'Change Order'!H:H,"Approved") -> 0 | G16: =IF(E16<>"",E16+F16,"") -> 589.95
A17: 016 | B17: G | C17: JOHN | D17: MDF CIRCLES | F17: =SUMIFS('Change Order'!G:G,'Change Order'!B:B,A17,'Change Order'!H:H,"Approved") -> 0 | G17: =IF(E17<>"",E17+F17,"")
A18: 017 | B18: G | C18: JOHN | D18: PLYWOOD PANELS | F18: =SUMIFS('Change Order'!G:G,'Change Order'!B:B,A18,'Change Order'!H:H,"Approved") -> 0 | G18: =IF(E18<>"",E18+F18,"")
A19: 018 | B19: G | C19: LMHMC | D19: MOB 2 STE 200 | E19: 6118 | F19: =SUMIFS('Change Order'!G:G,'Change Order'!B:B,A19,'Change Order'!H:H,"Approved") -> 0 | G19: =IF(E19<>"",E19+F19,"") -> 6118
A20: 019 | B20: G | C20: OREGON RESTORATION | D20: VANITY | E20: 1074 | F20: =SUMIFS('Change Order'!G:G,'Change Order'!B:B,A20,'Change Order'!H:H,"Approved") -> 0 | G20: =IF(E20<>"",E20+F20,"") -> 1074
A21: 020 | B21: P | C21: MARK HORYAT | D21: MISC | F21: =SUMIFS('Change Order'!G:G,'Change Order'!B:B,A21,'Change Order'!H:H,"Approved") -> 0 | G21: =IF(E21<>"",E21+F21,"")
A22: 021 | B22: G | C22: NORWEST | D22: TOC LAB REMODEL | E22: 3504 | F22: =SUMIFS('Change Order'!G:G,'Change Order'!B:B,A22,'Change Order'!H:H,"Approved") -> 0 | G22: =IF(E22<>"",E22+F22,"") -> 3504
A23: 022 | B23: G | C23: 5 STAR | D23: EMANUAL RM 5400 CASEWORK | E23: 5713 | F23: =SUMIFS('Change Order'!G:G,'Change Order'!B:B,A23,'Change Order'!H:H,"Approved") -> 0 | G23: =IF(E23<>"",E23+F23,"") -> 5713
A24: 023 | B24: P | C24: JOHN HOLTMANN | D24: GOLF CABINET | F24: =SUMIFS('Change Order'!G:G,'Change Order'!B:B,A24,'Change Order'!H:H,"Approved") -> 0 | G24: =IF(E24<>"",E24+F24,"")
A25: 024 | B25: G | C25: CCDC | D25: VOLCANO VIEW BOOKCASES | E25: 4114 | F25: =SUMIFS('Change Order'!G:G,'Change Order'!B:B,A25,'Change Order'!H:H,"Approved") -> 0 | G25: =IF(E25<>"",E25+F25,"") -> 4114
A26: 025 | B26: G | C26: SCHAFFRON CONST | D26: 2 DOORS | F26: =SUMIFS('Change Order'!G:G,'Change Order'!B:B,A26,'Change Order'!H:H,"Approved") -> 0 | G26: =IF(E26<>"",E26+F26,"")
A27: 026 | B27: G | C27: ESSEX | D27: BONNEVILLE ST JOHNS | E27: 3845 | F27: =SUMIFS('Change Order'!G:G,'Change Order'!B:B,A27,'Change Order'!H:H,"Approved") -> 0 | G27: =IF(E27<>"",E27+F27,"") -> 3845
A28: 027 | B28: G | C28: LMHMC | D28: MATERNITY CAB | E28: 1973 | F28: =SUMIFS('Change Order'!G:G,'Change Order'!B:B,A28,'Change Order'!H:H,"Approved") -> 0 | G28: =IF(E28<>"",E28+F28,"") -> 1973
A29: 028 | B29: G | C29: CCDC | D29: PACIFIC BLD SUITE 1012-1015 | E29: 9296 | F29: =SUMIFS('Change Order'!G:G,'Change Order'!B:B,A29,'Change Order'!H:H,"Approved") -> 0 | G29: =IF(E29<>"",E29+F29,"") -> 9296
A30: 029 | B30: G | C30: TRAINOR COMMERCIAL CONST. | D30: DESIGN WITHIN REACH | E30: 22923 | F30: =SUMIFS('Change Order'!G:G,'Change Order'!B:B,A30,'Change Order'!H:H,"Approved") -> 0 | G30: =IF(E30<>"",E30+F30,"") -> 22923 | H30: Q-26-035
A31: 030 | B31: J | C31: R. HAKES | D31: PACIFIC OFFICE AUTOMATION RENO | E31: 6657 | F31: =SUMIFS('Change Order'!G:G,'Change Order'!B:B,A31,'Change Order'!H:H,"Approved") -> 0 | G31: =IF(E31<>"",E31+F31,"") -> 6657 | H31: Q-26-043
A32: 031 | B32: J | C32: R. HAKES | D32: ST. ANDREWS CHURCH DR | E32: 13731 | F32: =SUMIFS('Change Order'!G:G,'Change Order'!B:B,A32,'Change Order'!H:H,"Approved") -> 0 | G32: =IF(E32<>"",E32+F32,"") -> 13731
A33: 032 | B33: G | C33: LMHMC | D33: FIV CABIN | F33: =SUMIFS('Change Order'!G:G,'Change Order'!B:B,A33,'Change Order'!H:H,"Approved") -> 0 | G33: =IF(E33<>"",E33+F33,"")
A34: 033 | B34: G | C34: 5 STAR | D34: UNITY LOBBY DRAWER BOX | E34: 157.5 | F34: =SUMIFS('Change Order'!G:G,'Change Order'!B:B,A34,'Change Order'!H:H,"Approved") -> 0 | G34: =IF(E34<>"",E34+F34,"") -> 157.5
A35: 034 | B35: G | C35: INLINE | D35: OFFICE REMODEL | E35: 4955 | F35: =SUMIFS('Change Order'!G:G,'Change Order'!B:B,A35,'Change Order'!H:H,"Approved") -> 0 | G35: =IF(E35<>"",E35+F35,"") -> 4955 | H35: Q-26-086
A36: 035 | B36: G | C36: BEAVERTON DENTAL | D36: MISC | F36: =SUMIFS('Change Order'!G:G,'Change Order'!B:B,A36,'Change Order'!H:H,"Approved") -> 0 | G36: =IF(E36<>"",E36+F36,"")
A37: 036 | B37: G | C37: ACC / PROV. GATEWAY | D37: MOB X-RAY | E37: 1746 | F37: =SUMIFS('Change Order'!G:G,'Change Order'!B:B,A37,'Change Order'!H:H,"Approved") -> 0 | G37: =IF(E37<>"",E37+F37,"") -> 1746
A38: 037 | B38: G | C38: AWE | D38: CUT PARTS | E38: 200 | F38: =SUMIFS('Change Order'!G:G,'Change Order'!B:B,A38,'Change Order'!H:H,"Approved") -> 0 | G38: =IF(E38<>"",E38+F38,"") -> 200
A39: 038 | B39: G | C39: LOIS | D39: G. TOP | F39: =SUMIFS('Change Order'!G:G,'Change Order'!B:B,A39,'Change Order'!H:H,"Approved") -> 0 | G39: =IF(E39<>"",E39+F39,"")
A40: 039 | B40: G | C40: ALOFT | D40: REFINISH DOOR | F40: =SUMIFS('Change Order'!G:G,'Change Order'!B:B,A40,'Change Order'!H:H,"Approved") -> 0 | G40: =IF(E40<>"",E40+F40,"")
A41: 040 | B41: G | C41: FOREST GROVE | D41: BREAK RM | E41: 4681 | F41: =SUMIFS('Change Order'!G:G,'Change Order'!B:B,A41,'Change Order'!H:H,"Approved") -> 0 | G41: =IF(E41<>"",E41+F41,"") -> 4681
A42: 041 | B42: G | C42: 5 STAR | D42: LEMC MOB 2 STE 550 | E42: 2300 | F42: =SUMIFS('Change Order'!G:G,'Change Order'!B:B,A42,'Change Order'!H:H,"Approved") -> 0 | G42: =IF(E42<>"",E42+F42,"") -> 2300
A43: 042 | B43: G | C43: ACC / LSMC | D43: OP PHARMACY | E43: 36209 | F43: =SUMIFS('Change Order'!G:G,'Change Order'!B:B,A43,'Change Order'!H:H,"Approved") -> 0 | G43: =IF(E43<>"",E43+F43,"") -> 36209
A44: 043 | B44: G | C44: JEFF RULE | D44: DOOR REPAIR | F44: =SUMIFS('Change Order'!G:G,'Change Order'!B:B,A44,'Change Order'!H:H,"Approved") -> 0 | G44: =IF(E44<>"",E44+F44,"")
A45: 044 | B45: P | C45: MARK ASPLUND | D45: CASEWORK | E45: T+M | G45: T+M
A46: 045 | B46: G | C46: LMHMC | D46: STAFF LOUNGE | E46: 3019 | F46: =SUMIFS('Change Order'!G:G,'Change Order'!B:B,A46,'Change Order'!H:H,"Approved") -> 0 | G46: =IF(E46<>"",E46+F46,"") -> 3019
A47: 046 | B47: G | C47: NORWEST | D47: ROSECITY HEAD & NECK SURGERY | E47: 26942 | F47: =SUMIFS('Change Order'!G:G,'Change Order'!B:B,A47,'Change Order'!H:H,"Approved") -> 0 | G47: =IF(E47<>"",E47+F47,"") -> 26942
A48: 047
A49: 048
A50: 049
A51: 050
A52: 051
A53: 052
A54: 053
A55: 054
A56: 055
A57: 056
A58: 057
A59: 058
... A71: J

Sheet Change Order
A1: CO # | B1: Job ID | C1: Client | D1: Project Name | E1: CO Description | F1: Date Submitted | G1: Amount ($) | H1: Status | I1: Approved Date | J1: Notes
A2: CO-26-001-01 | B2: Q-26-003 | C2: Viking | D2: Legacy Good Sam Pharmacy Retrofit | E2: Owner-directed scope addition — additional upper cabs Room 112 | G2: 2400 | H2: Pending
A3: CO-26-062-01 | B3: Q-26-062 | C3: Andersen | D3: LSMC OP Pharmacy | E3: ASI-01 - Add Full Height Cab with Lock, Pick-up windown shelving | F3: 46132 | G3: 2178 | H3: Pending
A4: CO # format: CO-YY-JJJ-NN (e.g. CO-26-003-01 = 2026, Job Q-26-003, CO #1)

Sheet Historical
A1: Year | B1: Total Bids | C1: Submitted | D1: Won | E1: Win Rate | F1: Total Won Value ($) | G1: Avg Bid Value ($) | H1: Notes
A2: 2024 | E2: =IFERROR(D2/C2,0) -> 0 | F2: 1861816 | H2: Full year revenue — manually recorded
A3: 2025 | B3: =COUNTA('2025 Bid Tracker'!D:D)-COUNTIF('2025 Bid Tracker'!D:D,"Project Name")-1-COUNTIF('2025 Bid Tracker'!G:G,"Budget") -> 143 | C3: =COUNTIFS('2025 Bid Tracker'!J:J,"Sent",'2025 Bid Tracker'!G:G,"<>Budget")+COUNTIFS('2025 Bid Tracker'!J:J,"Won",'2025 Bid Tracker'!G:G,"<>Budget") -> 93 | D3: =COUNTIFS('2025 Bid Tracker'!K:K,"✔",'2025 Bid Tracker'!G:G,"<>Budget") -> 17 | E3: =IFERROR(D3/C3,0) -> 0.1827957 | F3: =SUMIFS('2025 Bid Tracker'!M:M,'2025 Bid Tracker'!K:K,"✔",'2025 Bid Tracker'!G:G,"<>Budget")-'2025 Bid Tracker'!M126-'2025 Bid Tracker'!M183-'2025 Bid Tracker'!M125-'2025 Bid Tracker'!M154 -> 331875.97 | G3: =IFERROR(F3/D3,0) -> 19522.116 | H3: 2025 partial as of 9/4/25: $1,924,157 revenue. Powells PDX, Oregon Vascular, Greenburg Pediatric moved to 2026.
A4: 2026 | B4: =COUNTA('2026 Bid Tracker'!D:D)-COUNTIF('2026 Bid Tracker'!D:D,"Project Name")-1-COUNTIF('2026 Bid Tracker'!G:G,"Budget") -> 108 | C4: =COUNTIFS('2026 Bid Tracker'!J:J,"Sent",'2026 Bid Tracker'!G:G,"<>Budget")+COUNTIFS('2026 Bid Tracker'!J:J,"Won",'2026 Bid Tracker'!G:G,"<>Budget") -> 91 | D4: =COUNTIFS('2026 Bid Tracker'!K:K,"✔",'2026 Bid Tracker'!G:G,"<>Budget") -> 24 | E4: =IFERROR(D4/C4,0) -> 0.26373626 | F4: =SUMIFS('2026 Bid Tracker'!M:M,'2026 Bid Tracker'!K:K,"✔",'2026 Bid Tracker'!G:G,"<>Budget")+'2025 Bid Tracker'!M126+'2025 Bid Tracker'!M183+'2025 Bid Tracker'!M125+'2025 Bid Tracker'!M154 -> 549952 | G4: =IFERROR(F4/D4,0) -> 22914.667 | H4: Year in progress. Includes Powells PDX, Oregon Vascular, Greenburg Pediatric, TOC Path Lab from 2025 tracker (2026 revenue).

Sheet Dashboard
A1: Estimating Dashboard — 2026 YTD vs 2025
A2: Metric | B2: 2026 (YTD) | C2: 2025 (Full Year) | D2: Notes
A3: Total Bids Logged | B3: =COUNTA('2026 Bid Tracker'!D:D)-COUNTIF('2026 Bid Tracker'!D:D,"Project Name")-1 -> 131 | C3: =COUNTA('2025 Bid Tracker'!D:D)-COUNTIF('2025 Bid Tracker'!D:D,"Project Name")-1 -> 178
A4: Bids Submitted | B4: =COUNTIF('2026 Bid Tracker'!J:J,"Sent")+COUNTIF('2026 Bid Tracker'!J:J,"Won") -> 113 | C4: =COUNTIF('2025 Bid Tracker'!J:J,"Sent")+COUNTIF('2025 Bid Tracker'!J:J,"Won") -> 115
A5: Bids Won | B5: =COUNTIF('2026 Bid Tracker'!K:K,"✔") -> 25 | C5: =COUNTIF('2025 Bid Tracker'!K:K,"✔") -> 20
A6: Win Rate | B6: =IFERROR(B5/B4,0) -> 0.22123894 | C6: =IFERROR(C5/C4,0) -> 0.17391304 | D6: Won ÷ Submitted
A7: Total Won Value ($) | B7: =SUMIF('2026 Bid Tracker'!K:K,"✔",'2026 Bid Tracker'!M:M) -> 418192 | C7: =SUMIF('2025 Bid Tracker'!K:K,"✔",'2025 Bid Tracker'!M:M) -> 695332.97
A8: Avg Won Bid Value ($) | B8: =IFERROR(B7/B5,0) -> 16727.68 | C8: =IFERROR(C7/C5,0) -> 34766.648 | D8: Won Value ÷ Won Count
A9: Avg Est. Bid Size ($) | B9: =IFERROR(AVERAGEIF('2026 Bid Tracker'!M:M,">0",'2026 Bid Tracker'!M:M),0) -> 47193.336 | C9: =IFERROR(AVERAGEIF('2025 Bid Tracker'!M:M,">0",'2025 Bid Tracker'!M:M),0) -> 62148.86 | D9: Avg across all logged bids
A10: Active Jobs (Current Jobs) | B10: =COUNTA('Current Jobs'!B:B)-1 -> 46 | D10: From Current Jobs tab
A11: Total Active Contract Value ($) | B11: =IFERROR(SUM('Current Jobs'!H:H),0) -> 0 | D11: Incl. approved COs

Sheet Running TO-DO
A1: July | L1: August Mileage
L2: 45874 | M2: 26 | N2: Miles R/T | O2: Park Towers#211
L3: 45875 | M3: 22 | N3: Miles R/T | O3: PeaceHealth
L4: 45877 | M4: 65 | N4: Miles R/T | O4: Mill Plains Zoom | P4: Willamette Falls Pediatric Unit
L10: Total Mileage | M10: 113
L11: 2025 Rate | M11: 0.7 | N11: /Mile
M13: 79.1
A16: Potential New Jobs
A17: JDL | B17: New Seasons Treatment
A18: pacific Crest | B18: Pacific Center 5TH Floor
A19: Norwest | B19: Greenburg Pediatric Dentistry
